CMap2D.cpp
CMap2D.pyx
MANIFEST.in
README.md
circular_index.py
map2d.py
map2d_ros_tools.py
pose2d.py
pyproject.toml
setup.py
pymap2d.egg-info/PKG-INFO
pymap2d.egg-info/SOURCES.txt
pymap2d.egg-info/dependency_links.txt
pymap2d.egg-info/requires.txt
pymap2d.egg-info/top_level.txt
test/test_cmap2d.py