Metadata-Version: 2.1
Name: pymap2d
Version: 0.1.9
Summary: Tools for 2D maps
Home-page: https://github.com/danieldugas/pymap2d
Author: Daniel Dugas
License: UNKNOWN
Platform: UNKNOWN
